{
	"$schema": "http://schema.management.azure.com/schemas/2015-01-01/deploymentTemplate.json#",
	"contentVersion": "1.0.0.0",
	"parameters": {
		"factoryName": {
			"type": "string",
			"metadata": "Data Factory name",
			"defaultValue": "dataanshfactory"
		},
		"ls_onprem_file_password": {
			"type": "secureString",
			"metadata": "Secure string for 'password' of 'ls_onprem_file'"
		},
		"ls_onprem_file_properties_typeProperties_host": {
			"type": "string",
			"defaultValue": "D:\\AnshLambaFiles"
		},
		"ls_onprem_file_properties_typeProperties_userId": {
			"type": "string",
			"defaultValue": "swadhinpolai444@gmail.com"
		}
	},
	"variables": {
		"factoryId": "[concat('Microsoft.DataFactory/factories/', parameters('factoryName'))]"
	},
	"resources": [
		{
			"name": "[concat(parameters('factoryName'), '/ds_sinkfilecheck')]",
			"type": "Microsoft.DataFactory/factories/datasets",
			"apiVersion": "2018-06-01",
			"properties": {
				"linkedServiceName": {
					"referenceName": "ls_datalake",
					"type": "LinkedServiceReference"
				},
				"annotations": [],
				"type": "DelimitedText",
				"typeProperties": {
					"location": {
						"type": "AzureBlobFSLocation",
						"fileName": "filename.csv",
						"fileSystem": "Filename"
					},
					"columnDelimiter": ",",
					"escapeChar": "\\",
					"firstRowAsHeader": true,
					"quoteChar": "\""
				},
				"schema": []
			},
			"dependsOn": []
		},
		{
			"name": "[concat(parameters('factoryName'), '/ds_sqllookup')]",
			"type": "Microsoft.DataFactory/factories/datasets",
			"apiVersion": "2018-06-01",
			"properties": {
				"linkedServiceName": {
					"referenceName": "ls_sqldb",
					"type": "LinkedServiceReference"
				},
				"annotations": [],
				"type": "AzureSqlTable",
				"schema": [],
				"typeProperties": {
					"schema": "dbo",
					"table": "orders_final"
				}
			},
			"dependsOn": []
		},
		{
			"name": "[concat(parameters('factoryName'), '/ds_sqlsource')]",
			"type": "Microsoft.DataFactory/factories/datasets",
			"apiVersion": "2018-06-01",
			"properties": {
				"linkedServiceName": {
					"referenceName": "ls_sqldb",
					"type": "LinkedServiceReference"
				},
				"annotations": [],
				"type": "AzureSqlTable",
				"schema": [],
				"typeProperties": {}
			},
			"dependsOn": []
		},
		{
			"name": "[concat(parameters('factoryName'), '/ls_onprem_file')]",
			"type": "Microsoft.DataFactory/factories/linkedServices",
			"apiVersion": "2018-06-01",
			"properties": {
				"annotations": [],
				"type": "FileServer",
				"typeProperties": {
					"host": "[parameters('ls_onprem_file_properties_typeProperties_host')]",
					"userId": "[parameters('ls_onprem_file_properties_typeProperties_userId')]",
					"password": {
						"type": "SecureString",
						"value": "[parameters('ls_onprem_file_password')]"
					}
				},
				"connectVia": {
					"referenceName": "Ansh-selfhosted",
					"type": "IntegrationRuntimeReference"
				}
			},
			"dependsOn": []
		},
		{
			"name": "[concat(parameters('factoryName'), '/Data Serving')]",
			"type": "Microsoft.DataFactory/factories/dataflows",
			"apiVersion": "2018-06-01",
			"properties": {
				"type": "MappingDataFlow",
				"typeProperties": {
					"sources": [
						{
							"linkedService": {
								"referenceName": "ls_datalake",
								"type": "LinkedServiceReference"
							},
							"name": "DimAirline"
						},
						{
							"linkedService": {
								"referenceName": "ls_datalake",
								"type": "LinkedServiceReference"
							},
							"name": "DimFlights"
						},
						{
							"linkedService": {
								"referenceName": "ls_datalake",
								"type": "LinkedServiceReference"
							},
							"name": "FactBookings"
						}
					],
					"sinks": [
						{
							"linkedService": {
								"referenceName": "ls_datalake",
								"type": "LinkedServiceReference"
							},
							"name": "AirlineSinkGold"
						},
						{
							"linkedService": {
								"referenceName": "ls_datalake",
								"type": "LinkedServiceReference"
							},
							"name": "FlightSinkGold"
						}
					],
					"transformations": [
						{
							"name": "AirLineJoin"
						},
						{
							"name": "selectAirlineID"
						},
						{
							"name": "aggregateAirline"
						},
						{
							"name": "Ranking"
						},
						{
							"name": "filterTop5"
						},
						{
							"name": "join1"
						},
						{
							"name": "selectFlightID"
						},
						{
							"name": "aggregateFlightNumber"
						},
						{
							"name": "window1"
						},
						{
							"name": "FlightTop5"
						},
						{
							"name": "UpsertAirline"
						},
						{
							"name": "UpsertFlight"
						}
					],
					"scriptLines": [
						"source(output(",
						"          airline_id as short,",
						"          airline_name as string,",
						"          country as string",
						"     ),",
						"     allowSchemaDrift: true,",
						"     validateSchema: false,",
						"     ignoreNoFilesFound: false,",
						"     format: 'delta',",
						"     fileSystem: 'silver',",
						"     folderPath: 'DimAirline') ~> DimAirline",
						"source(output(",
						"          flight_id as short,",
						"          flight_number as string,",
						"          departure_timestamp as string,",
						"          arrival_timestamp as string",
						"     ),",
						"     allowSchemaDrift: true,",
						"     validateSchema: false,",
						"     ignoreNoFilesFound: false,",
						"     format: 'delta',",
						"     fileSystem: 'silver',",
						"     folderPath: 'DimFlights') ~> DimFlights",
						"source(output(",
						"          booking_id as integer,",
						"          passenger_id as integer,",
						"          flight_id as integer,",
						"          airline_id as integer,",
						"          origin_airport_id as integer,",
						"          destination_airport_id as integer,",
						"          booking_date as date,",
						"          ticket_cost as integer,",
						"          flight_duration_mins as integer,",
						"          checkin_status as string",
						"     ),",
						"     allowSchemaDrift: true,",
						"     validateSchema: false,",
						"     ignoreNoFilesFound: false,",
						"     format: 'delta',",
						"     fileSystem: 'silver',",
						"     folderPath: 'FactBooking') ~> FactBookings",
						"DimAirline, FactBookings join(DimAirline@airline_id == FactBookings@airline_id,",
						"     joinType:'right',",
						"     matchType:'exact',",
						"     ignoreSpaces: false,",
						"     broadcast: 'auto')~> AirLineJoin",
						"AirLineJoin select(mapColumn(",
						"          airline_name,",
						"          country,",
						"          booking_id,",
						"          passenger_id,",
						"          flight_id,",
						"          airline_id = FactBookings@airline_id,",
						"          origin_airport_id,",
						"          destination_airport_id,",
						"          booking_date,",
						"          ticket_cost,",
						"          flight_duration_mins,",
						"          checkin_status",
						"     ),",
						"     skipDuplicateMapInputs: true,",
						"     skipDuplicateMapOutputs: true) ~> selectAirlineID",
						"selectAirlineID aggregate(groupBy(airline_name),",
						"     Total_Sales = sum(ticket_cost)) ~> aggregateAirline",
						"aggregateAirline window(desc(Total_Sales, true),",
						"     Top = denseRank()) ~> Ranking",
						"Ranking filter(Top < 6) ~> filterTop5",
						"DimFlights, FactBookings join(DimFlights@flight_id == FactBookings@flight_id,",
						"     joinType:'left',",
						"     matchType:'exact',",
						"     ignoreSpaces: false,",
						"     broadcast: 'auto')~> join1",
						"join1 select(mapColumn(",
						"          flight_id = DimFlights@flight_id,",
						"          flight_number,",
						"          departure_timestamp,",
						"          arrival_timestamp,",
						"          booking_id,",
						"          passenger_id,",
						"          airline_id,",
						"          origin_airport_id,",
						"          destination_airport_id,",
						"          booking_date,",
						"          ticket_cost,",
						"          flight_duration_mins,",
						"          checkin_status",
						"     ),",
						"     skipDuplicateMapInputs: true,",
						"     skipDuplicateMapOutputs: true) ~> selectFlightID",
						"selectFlightID aggregate(groupBy(flight_number),",
						"     Top_Flight = sum(ticket_cost)) ~> aggregateFlightNumber",
						"aggregateFlightNumber window(desc(Top_Flight, true),",
						"     Ranking_Flight = denseRank()) ~> window1",
						"window1 filter({Ranking_Flight} < 6) ~> FlightTop5",
						"filterTop5 alterRow(insertIf(1==1)) ~> UpsertAirline",
						"FlightTop5 alterRow(insertIf(1==1)) ~> UpsertFlight",
						"UpsertAirline sink(allowSchemaDrift: true,",
						"     validateSchema: false,",
						"     format: 'delta',",
						"     fileSystem: 'gold',",
						"     folderPath: 'AirlineGold',",
						"     overwrite: true,",
						"     mergeSchema: false,",
						"     autoCompact: false,",
						"     optimizedWrite: false,",
						"     vacuum: 0,",
						"     deletable: false,",
						"     insertable: true,",
						"     updateable: false,",
						"     upsertable: false,",
						"     keys:['airline_name'],",
						"     umask: 0022,",
						"     preCommands: [],",
						"     postCommands: [],",
						"     skipDuplicateMapInputs: true,",
						"     skipDuplicateMapOutputs: true) ~> AirlineSinkGold",
						"UpsertFlight sink(allowSchemaDrift: true,",
						"     validateSchema: false,",
						"     format: 'delta',",
						"     fileSystem: 'gold',",
						"     folderPath: 'FlightGold',",
						"     overwrite: true,",
						"     mergeSchema: false,",
						"     autoCompact: false,",
						"     optimizedWrite: false,",
						"     vacuum: 0,",
						"     deletable: false,",
						"     insertable: true,",
						"     updateable: false,",
						"     upsertable: false,",
						"     keys:['flight_number'],",
						"     umask: 0022,",
						"     preCommands: [],",
						"     postCommands: [],",
						"     skipDuplicateMapInputs: true,",
						"     skipDuplicateMapOutputs: true) ~> FlightSinkGold"
					]
				}
			},
			"dependsOn": []
		},
		{
			"name": "[concat(parameters('factoryName'), '/10_fetch filename')]",
			"type": "Microsoft.DataFactory/factories/pipelines",
			"apiVersion": "2018-06-01",
			"properties": {
				"activities": [
					{
						"name": "Get Metadata1",
						"type": "GetMetadata",
						"dependsOn": [],
						"policy": {
							"timeout": "0.12:00:00",
							"retry": 0,
							"retryIntervalInSeconds": 30,
							"secureOutput": false,
							"secureInput": false
						},
						"userProperties": [],
						"typeProperties": {
							"dataset": {
								"referenceName": "ds_fetchfile_input",
								"type": "DatasetReference",
								"parameters": {}
							},
							"fieldList": [
								"childItems"
							],
							"storeSettings": {
								"type": "AzureBlobFSReadSettings",
								"recursive": true,
								"enablePartitionDiscovery": false
							},
							"formatSettings": {
								"type": "DelimitedTextReadSettings"
							}
						}
					},
					{
						"name": "ForEach1",
						"type": "ForEach",
						"dependsOn": [
							{
								"activity": "Get Metadata1",
								"dependencyConditions": [
									"Succeeded"
								]
							}
						],
						"userProperties": [],
						"typeProperties": {
							"items": {
								"value": "@activity('Get Metadata1').output.childItems",
								"type": "Expression"
							},
							"activities": [
								{
									"name": "Append variable1",
									"type": "AppendVariable",
									"dependsOn": [],
									"userProperties": [],
									"typeProperties": {
										"variableName": "Filenamevar",
										"value": {
											"value": "@item().name",
											"type": "Expression"
										}
									}
								},
								{
									"name": "Copy data1",
									"type": "Copy",
									"dependsOn": [
										{
											"activity": "Append variable1",
											"dependencyConditions": [
												"Succeeded"
											]
										}
									],
									"policy": {
										"timeout": "0.12:00:00",
										"retry": 0,
										"retryIntervalInSeconds": 30,
										"secureOutput": false,
										"secureInput": false
									},
									"userProperties": [],
									"typeProperties": {
										"source": {
											"type": "DelimitedTextSource",
											"additionalColumns": [
												{
													"name": "FileName",
													"value": {
														"value": "@{variables('Filenamevar')}",
														"type": "Expression"
													}
												}
											],
											"storeSettings": {
												"type": "AzureBlobFSReadSettings",
												"recursive": true,
												"enablePartitionDiscovery": false
											},
											"formatSettings": {
												"type": "DelimitedTextReadSettings"
											}
										},
										"sink": {
											"type": "DelimitedTextSink",
											"storeSettings": {
												"type": "AzureBlobFSWriteSettings"
											},
											"formatSettings": {
												"type": "DelimitedTextWriteSettings",
												"quoteAllText": true,
												"fileExtension": ".txt"
											}
										},
										"enableStaging": false,
										"translator": {
											"type": "TabularTranslator",
											"mappings": [
												{
													"source": {
														"name": "FileName",
														"type": "String"
													},
													"sink": {
														"name": "FileName",
														"type": "String",
														"physicalType": "String"
													}
												}
											],
											"typeConversion": true,
											"typeConversionSettings": {
												"allowDataTruncation": true,
												"treatBooleanAsNumber": false
											}
										}
									},
									"inputs": [
										{
											"referenceName": "ds_dummy",
											"type": "DatasetReference",
											"parameters": {}
										}
									],
									"outputs": [
										{
											"referenceName": "ds_sinkfilecheck",
											"type": "DatasetReference",
											"parameters": {}
										}
									]
								}
							]
						}
					}
				],
				"policy": {
					"elapsedTimeMetric": {}
				},
				"variables": {
					"Filenamevar": {
						"type": "Array"
					}
				},
				"annotations": [],
				"lastPublishTime": "2026-01-02T14:59:09Z"
			},
			"dependsOn": [
				"[concat(variables('factoryId'), '/datasets/ds_sinkfilecheck')]"
			]
		},
		{
			"name": "[concat(parameters('factoryName'), '/12_latestfile')]",
			"type": "Microsoft.DataFactory/factories/pipelines",
			"apiVersion": "2018-06-01",
			"properties": {
				"activities": [
					{
						"name": "Get Metadata1",
						"type": "GetMetadata",
						"dependsOn": [],
						"policy": {
							"timeout": "0.12:00:00",
							"retry": 0,
							"retryIntervalInSeconds": 30,
							"secureOutput": false,
							"secureInput": false
						},
						"userProperties": [],
						"typeProperties": {
							"dataset": {
								"referenceName": "ds_fetchfile_input",
								"type": "DatasetReference",
								"parameters": {}
							},
							"fieldList": [
								"childItems"
							],
							"storeSettings": {
								"type": "AzureBlobFSReadSettings",
								"recursive": true,
								"enablePartitionDiscovery": false
							},
							"formatSettings": {
								"type": "DelimitedTextReadSettings"
							}
						}
					},
					{
						"name": "ForEach1",
						"type": "ForEach",
						"dependsOn": [
							{
								"activity": "Get Metadata1",
								"dependencyConditions": [
									"Succeeded"
								]
							}
						],
						"userProperties": [],
						"typeProperties": {
							"items": {
								"value": "@activity('Get Metadata1').output.childItems",
								"type": "Expression"
							},
							"activities": [
								{
									"name": "Get Metadata2",
									"type": "GetMetadata",
									"dependsOn": [],
									"policy": {
										"timeout": "0.12:00:00",
										"retry": 0,
										"retryIntervalInSeconds": 30,
										"secureOutput": false,
										"secureInput": false
									},
									"userProperties": [],
									"typeProperties": {
										"dataset": {
											"referenceName": "ds_fileinput_par",
											"type": "DatasetReference",
											"parameters": {
												"p_filename": {
													"value": "@item().name",
													"type": "Expression"
												}
											}
										},
										"fieldList": [
											"lastModified",
											"itemName"
										],
										"storeSettings": {
											"type": "AzureBlobFSReadSettings",
											"recursive": true,
											"enablePartitionDiscovery": false
										},
										"formatSettings": {
											"type": "DelimitedTextReadSettings"
										}
									}
								},
								{
									"name": "If Condition1",
									"type": "IfCondition",
									"dependsOn": [
										{
											"activity": "Get Metadata2",
											"dependencyConditions": [
												"Succeeded"
											]
										}
									],
									"userProperties": [],
									"typeProperties": {
										"expression": {
											"value": "@greater(activity('Get Metadata2').output.lastModified,variables('Ref_datetime'))",
											"type": "Expression"
										},
										"ifTrueActivities": [
											{
												"name": "Set variable1",
												"type": "SetVariable",
												"dependsOn": [],
												"policy": {
													"secureOutput": false,
													"secureInput": false
												},
												"userProperties": [],
												"typeProperties": {
													"variableName": "Ref_datetime",
													"value": {
														"value": "@activity('Get Metadata2').output.lastModified",
														"type": "Expression"
													}
												}
											},
											{
												"name": "Set variable2",
												"type": "SetVariable",
												"dependsOn": [
													{
														"activity": "Set variable1",
														"dependencyConditions": [
															"Succeeded"
														]
													}
												],
												"policy": {
													"secureOutput": false,
													"secureInput": false
												},
												"userProperties": [],
												"typeProperties": {
													"variableName": "latestfile",
													"value": {
														"value": "@activity('Get Metadata2').output.itemName",
														"type": "Expression"
													}
												}
											}
										]
									}
								}
							]
						}
					},
					{
						"name": "Copy data1",
						"type": "Copy",
						"dependsOn": [
							{
								"activity": "ForEach1",
								"dependencyConditions": [
									"Succeeded"
								]
							}
						],
						"policy": {
							"timeout": "0.12:00:00",
							"retry": 0,
							"retryIntervalInSeconds": 30,
							"secureOutput": false,
							"secureInput": false
						},
						"userProperties": [],
						"typeProperties": {
							"source": {
								"type": "DelimitedTextSource",
								"storeSettings": {
									"type": "AzureBlobFSReadSettings",
									"recursive": true,
									"enablePartitionDiscovery": false
								},
								"formatSettings": {
									"type": "DelimitedTextReadSettings"
								}
							},
							"sink": {
								"type": "DelimitedTextSink",
								"storeSettings": {
									"type": "AzureBlobFSWriteSettings"
								},
								"formatSettings": {
									"type": "DelimitedTextWriteSettings",
									"quoteAllText": true,
									"fileExtension": ".txt"
								}
							},
							"enableStaging": false,
							"translator": {
								"type": "TabularTranslator",
								"typeConversion": true,
								"typeConversionSettings": {
									"allowDataTruncation": true,
									"treatBooleanAsNumber": false
								}
							}
						},
						"inputs": [
							{
								"referenceName": "ds_fileinput_par",
								"type": "DatasetReference",
								"parameters": {
									"p_filename": {
										"value": "@variables('latestfile')",
										"type": "Expression"
									}
								}
							}
						],
						"outputs": [
							{
								"referenceName": "ds_latest_file_sink",
								"type": "DatasetReference",
								"parameters": {
									"p_filename": {
										"value": "@variables('latestfile')",
										"type": "Expression"
									}
								}
							}
						]
					}
				],
				"policy": {
					"elapsedTimeMetric": {}
				},
				"variables": {
					"latestfile": {
						"type": "String"
					},
					"Ref_datetime": {
						"type": "String",
						"defaultValue": "1900-01-01 00:00:00"
					}
				},
				"annotations": [],
				"lastPublishTime": "2026-01-03T09:49:08Z"
			},
			"dependsOn": []
		},
		{
			"name": "[concat(parameters('factoryName'), '/13_1_latestfile')]",
			"type": "Microsoft.DataFactory/factories/pipelines",
			"apiVersion": "2018-06-01",
			"properties": {
				"activities": [
					{
						"name": "Get Metadata1",
						"type": "GetMetadata",
						"dependsOn": [],
						"policy": {
							"timeout": "0.12:00:00",
							"retry": 0,
							"retryIntervalInSeconds": 30,
							"secureOutput": false,
							"secureInput": false
						},
						"userProperties": [],
						"typeProperties": {
							"dataset": {
								"referenceName": "ds_dynamic_folder",
								"type": "DatasetReference",
								"parameters": {
									"Foldername": {
										"value": "@pipeline().parameters.p_foldername",
										"type": "Expression"
									}
								}
							},
							"fieldList": [
								"childItems"
							],
							"storeSettings": {
								"type": "AzureBlobFSReadSettings",
								"recursive": true,
								"enablePartitionDiscovery": false
							},
							"formatSettings": {
								"type": "DelimitedTextReadSettings"
							}
						}
					},
					{
						"name": "ForEach1",
						"type": "ForEach",
						"dependsOn": [
							{
								"activity": "Get Metadata1",
								"dependencyConditions": [
									"Succeeded"
								]
							}
						],
						"userProperties": [],
						"typeProperties": {
							"items": {
								"value": "@activity('Get Metadata1').output.childItems",
								"type": "Expression"
							},
							"activities": [
								{
									"name": "Get Metadata2",
									"type": "GetMetadata",
									"dependsOn": [],
									"policy": {
										"timeout": "0.12:00:00",
										"retry": 0,
										"retryIntervalInSeconds": 30,
										"secureOutput": false,
										"secureInput": false
									},
									"userProperties": [],
									"typeProperties": {
										"dataset": {
											"referenceName": "ds_folder_file",
											"type": "DatasetReference",
											"parameters": {
												"p_foldername": {
													"value": "@pipeline().parameters.p_foldername",
													"type": "Expression"
												},
												"p_filename": {
													"value": "@item().name",
													"type": "Expression"
												}
											}
										},
										"fieldList": [
											"lastModified",
											"itemName"
										],
										"storeSettings": {
											"type": "AzureBlobFSReadSettings",
											"recursive": true,
											"enablePartitionDiscovery": false
										},
										"formatSettings": {
											"type": "DelimitedTextReadSettings"
										}
									}
								},
								{
									"name": "If Condition1",
									"type": "IfCondition",
									"dependsOn": [
										{
											"activity": "Get Metadata2",
											"dependencyConditions": [
												"Succeeded"
											]
										}
									],
									"userProperties": [],
									"typeProperties": {
										"expression": {
											"value": "@greater(activity('Get Metadata2').output.lastModified,variables('Ref_datetime'))",
											"type": "Expression"
										},
										"ifTrueActivities": [
											{
												"name": "Set variable1",
												"type": "SetVariable",
												"dependsOn": [],
												"policy": {
													"secureOutput": false,
													"secureInput": false
												},
												"userProperties": [],
												"typeProperties": {
													"variableName": "Ref_datetime",
													"value": {
														"value": "@activity('Get Metadata2').output.lastModified",
														"type": "Expression"
													}
												}
											},
											{
												"name": "Set variable2",
												"type": "SetVariable",
												"dependsOn": [
													{
														"activity": "Set variable1",
														"dependencyConditions": [
															"Succeeded"
														]
													}
												],
												"policy": {
													"secureOutput": false,
													"secureInput": false
												},
												"userProperties": [],
												"typeProperties": {
													"variableName": "latestfile",
													"value": {
														"value": "@activity('Get Metadata2').output.itemName",
														"type": "Expression"
													}
												}
											}
										]
									}
								}
							]
						}
					},
					{
						"name": "Copy data1",
						"type": "Copy",
						"dependsOn": [
							{
								"activity": "ForEach1",
								"dependencyConditions": [
									"Succeeded"
								]
							}
						],
						"policy": {
							"timeout": "0.12:00:00",
							"retry": 0,
							"retryIntervalInSeconds": 30,
							"secureOutput": false,
							"secureInput": false
						},
						"userProperties": [],
						"typeProperties": {
							"source": {
								"type": "DelimitedTextSource",
								"storeSettings": {
									"type": "AzureBlobFSReadSettings",
									"recursive": true,
									"enablePartitionDiscovery": false
								},
								"formatSettings": {
									"type": "DelimitedTextReadSettings"
								}
							},
							"sink": {
								"type": "DelimitedTextSink",
								"storeSettings": {
									"type": "AzureBlobFSWriteSettings"
								},
								"formatSettings": {
									"type": "DelimitedTextWriteSettings",
									"quoteAllText": true,
									"fileExtension": ".txt"
								}
							},
							"enableStaging": false,
							"translator": {
								"type": "TabularTranslator",
								"typeConversion": true,
								"typeConversionSettings": {
									"allowDataTruncation": true,
									"treatBooleanAsNumber": false
								}
							}
						},
						"inputs": [
							{
								"referenceName": "ds_folder_file",
								"type": "DatasetReference",
								"parameters": {
									"p_foldername": {
										"value": "@pipeline().parameters.p_foldername",
										"type": "Expression"
									},
									"p_filename": {
										"value": "@variables('latestfile')",
										"type": "Expression"
									}
								}
							}
						],
						"outputs": [
							{
								"referenceName": "ds_output_mul",
								"type": "DatasetReference",
								"parameters": {
									"p_filename": {
										"value": "@variables('latestfile')",
										"type": "Expression"
									}
								}
							}
						]
					}
				],
				"policy": {
					"elapsedTimeMetric": {}
				},
				"parameters": {
					"p_foldername": {
						"type": "string"
					}
				},
				"variables": {
					"latestfile": {
						"type": "String"
					},
					"Ref_datetime": {
						"type": "String",
						"defaultValue": "1900-01-01 00:00:00"
					}
				},
				"annotations": [],
				"lastPublishTime": "2026-01-03T14:44:41Z"
			},
			"dependsOn": []
		},
		{
			"name": "[concat(parameters('factoryName'), '/14_latestmodi')]",
			"type": "Microsoft.DataFactory/factories/pipelines",
			"apiVersion": "2018-06-01",
			"properties": {
				"activities": [
					{
						"name": "Get Metadata1",
						"type": "GetMetadata",
						"dependsOn": [],
						"policy": {
							"timeout": "0.12:00:00",
							"retry": 0,
							"retryIntervalInSeconds": 30,
							"secureOutput": false,
							"secureInput": false
						},
						"userProperties": [],
						"typeProperties": {
							"dataset": {
								"referenceName": "ds_fetchfile_input",
								"type": "DatasetReference",
								"parameters": {}
							},
							"fieldList": [
								"childItems"
							],
							"storeSettings": {
								"type": "AzureBlobFSReadSettings",
								"recursive": true,
								"enablePartitionDiscovery": false
							},
							"formatSettings": {
								"type": "DelimitedTextReadSettings"
							}
						}
					},
					{
						"name": "ForEach1",
						"type": "ForEach",
						"dependsOn": [
							{
								"activity": "Get Metadata1",
								"dependencyConditions": [
									"Succeeded"
								]
							}
						],
						"userProperties": [],
						"typeProperties": {
							"items": {
								"value": "@activity('Get Metadata1').output.childItems",
								"type": "Expression"
							},
							"activities": [
								{
									"name": "Get Metadata2",
									"type": "GetMetadata",
									"dependsOn": [],
									"policy": {
										"timeout": "0.12:00:00",
										"retry": 0,
										"retryIntervalInSeconds": 30,
										"secureOutput": false,
										"secureInput": false
									},
									"userProperties": [],
									"typeProperties": {
										"dataset": {
											"referenceName": "ds_inputparm",
											"type": "DatasetReference",
											"parameters": {
												"p_filename": {
													"value": "@item().name",
													"type": "Expression"
												}
											}
										},
										"fieldList": [
											"lastModified",
											"itemName"
										],
										"storeSettings": {
											"type": "AzureBlobFSReadSettings",
											"recursive": true,
											"enablePartitionDiscovery": false
										},
										"formatSettings": {
											"type": "DelimitedTextReadSettings"
										}
									}
								},
								{
									"name": "Lookup1",
									"type": "Lookup",
									"dependsOn": [
										{
											"activity": "Get Metadata2",
											"dependencyConditions": [
												"Succeeded"
											]
										}
									],
									"policy": {
										"timeout": "0.12:00:00",
										"retry": 0,
										"retryIntervalInSeconds": 30,
										"secureOutput": false,
										"secureInput": false
									},
									"userProperties": [],
									"typeProperties": {
										"source": {
											"type": "AzureSqlSource",
											"sqlReaderQuery": {
												"value": "if object_id ('dbo.TopNfiles') is NULL create table dbo.TopNfiles(itemName varchar(20), lastModifedDatetime datetime); insert into dbo.TopNfiles select '@{activity('Get Metadata2').output.itemName}','@{formatDateTime(activity('Get Metadata2').output.lastModified,'yyyy-MM-dd HH:mm:ss')}'; select 1 as output;",
												"type": "Expression"
											},
											"queryTimeout": "02:00:00",
											"partitionOption": "None"
										},
										"dataset": {
											"referenceName": "AzureSqlTable1",
											"type": "DatasetReference",
											"parameters": {}
										}
									}
								}
							]
						}
					},
					{
						"name": "Lookup2",
						"type": "Lookup",
						"dependsOn": [
							{
								"activity": "ForEach1",
								"dependencyConditions": [
									"Succeeded"
								]
							}
						],
						"policy": {
							"timeout": "0.12:00:00",
							"retry": 0,
							"retryIntervalInSeconds": 30,
							"secureOutput": false,
							"secureInput": false
						},
						"userProperties": [],
						"typeProperties": {
							"source": {
								"type": "AzureSqlSource",
								"sqlReaderQuery": {
									"value": "SELECT TOP 3 * from TopNfiles order by desc;",
									"type": "Expression"
								},
								"queryTimeout": "02:00:00",
								"partitionOption": "None"
							},
							"dataset": {
								"referenceName": "AzureSqlTable1",
								"type": "DatasetReference",
								"parameters": {}
							},
							"firstRowOnly": false
						}
					}
				],
				"policy": {
					"elapsedTimeMetric": {}
				},
				"annotations": [],
				"lastPublishTime": "2026-01-04T14:46:27Z"
			},
			"dependsOn": []
		},
		{
			"name": "[concat(parameters('factoryName'), '/7_EmptyNonEmpty')]",
			"type": "Microsoft.DataFactory/factories/pipelines",
			"apiVersion": "2018-06-01",
			"properties": {
				"activities": [
					{
						"name": "Get Metadata1",
						"type": "GetMetadata",
						"dependsOn": [],
						"policy": {
							"timeout": "0.12:00:00",
							"retry": 0,
							"retryIntervalInSeconds": 30,
							"secureOutput": false,
							"secureInput": false
						},
						"userProperties": [],
						"typeProperties": {
							"dataset": {
								"referenceName": "ds_folderinside",
								"type": "DatasetReference",
								"parameters": {}
							},
							"fieldList": [
								"childItems"
							],
							"storeSettings": {
								"type": "AzureBlobFSReadSettings",
								"recursive": true,
								"enablePartitionDiscovery": false
							},
							"formatSettings": {
								"type": "DelimitedTextReadSettings"
							}
						}
					},
					{
						"name": "ForEach1",
						"type": "ForEach",
						"dependsOn": [
							{
								"activity": "Get Metadata1",
								"dependencyConditions": [
									"Succeeded"
								]
							}
						],
						"userProperties": [],
						"typeProperties": {
							"items": {
								"value": "@activity('Get Metadata1').output.childItems",
								"type": "Expression"
							},
							"activities": [
								{
									"name": "Get Metadata2",
									"type": "GetMetadata",
									"dependsOn": [],
									"policy": {
										"timeout": "0.12:00:00",
										"retry": 0,
										"retryIntervalInSeconds": 30,
										"secureOutput": false,
										"secureInput": false
									},
									"userProperties": [],
									"typeProperties": {
										"dataset": {
											"referenceName": "DelimitedText1",
											"type": "DatasetReference",
											"parameters": {
												"p_foldername": {
													"value": "@item().name",
													"type": "Expression"
												}
											}
										},
										"fieldList": [
											"childItems"
										],
										"storeSettings": {
											"type": "AzureBlobFSReadSettings",
											"recursive": true,
											"enablePartitionDiscovery": false
										},
										"formatSettings": {
											"type": "DelimitedTextReadSettings"
										}
									}
								},
								{
									"name": "If Condition1",
									"type": "IfCondition",
									"dependsOn": [
										{
											"activity": "Get Metadata2",
											"dependencyConditions": [
												"Succeeded"
											]
										}
									],
									"userProperties": [],
									"typeProperties": {
										"expression": {
											"value": "@empty(activity('Get Metadata2').output.childItems)",
											"type": "Expression"
										},
										"ifFalseActivities": [
											{
												"name": "Append Non Empty",
												"type": "AppendVariable",
												"dependsOn": [],
												"userProperties": [],
												"typeProperties": {
													"variableName": "NonEmptyFolder",
													"value": {
														"value": "@item().name",
														"type": "Expression"
													}
												}
											}
										],
										"ifTrueActivities": [
											{
												"name": "Append Empty",
												"type": "AppendVariable",
												"dependsOn": [],
												"userProperties": [],
												"typeProperties": {
													"variableName": "EmptyFolder",
													"value": {
														"value": "@item().name",
														"type": "Expression"
													}
												}
											}
										]
									}
								}
							]
						}
					},
					{
						"name": "Copy to AzureSQL",
						"type": "Copy",
						"dependsOn": [
							{
								"activity": "ForEach1",
								"dependencyConditions": [
									"Succeeded"
								]
							}
						],
						"policy": {
							"timeout": "0.12:00:00",
							"retry": 0,
							"retryIntervalInSeconds": 30,
							"secureOutput": false,
							"secureInput": false
						},
						"userProperties": [],
						"typeProperties": {
							"source": {
								"type": "DelimitedTextSource",
								"additionalColumns": [
									{
										"name": "Empty Folder",
										"value": {
											"value": "@variables('EmptyFolder')",
											"type": "Expression"
										}
									},
									{
										"name": "NonEmpty Folder",
										"value": {
											"value": "@variables('NonEmptyFolder')",
											"type": "Expression"
										}
									}
								],
								"storeSettings": {
									"type": "AzureBlobFSReadSettings",
									"recursive": true,
									"enablePartitionDiscovery": false
								},
								"formatSettings": {
									"type": "DelimitedTextReadSettings"
								}
							},
							"sink": {
								"type": "AzureSqlSink",
								"writeBehavior": "insert",
								"sqlWriterUseTableLock": false,
								"tableOption": "autoCreate",
								"disableMetricsCollection": false
							},
							"enableStaging": false,
							"translator": {
								"type": "TabularTranslator",
								"typeConversion": true,
								"typeConversionSettings": {
									"allowDataTruncation": true,
									"treatBooleanAsNumber": false
								}
							}
						},
						"inputs": [
							{
								"referenceName": "ds_emptychek",
								"type": "DatasetReference",
								"parameters": {}
							}
						],
						"outputs": [
							{
								"referenceName": "AzureSqlTable1",
								"type": "DatasetReference",
								"parameters": {}
							}
						]
					}
				],
				"policy": {
					"elapsedTimeMetric": {}
				},
				"variables": {
					"EmptyFolder": {
						"type": "Array"
					},
					"NonEmptyFolder": {
						"type": "Array"
					}
				},
				"annotations": [],
				"lastPublishTime": "2025-12-28T09:14:45Z"
			},
			"dependsOn": []
		},
		{
			"name": "[concat(parameters('factoryName'), '/8_filestatus')]",
			"type": "Microsoft.DataFactory/factories/pipelines",
			"apiVersion": "2018-06-01",
			"properties": {
				"activities": [
					{
						"name": "Until1",
						"type": "Until",
						"dependsOn": [],
						"userProperties": [],
						"typeProperties": {
							"expression": {
								"value": "@bool(variables('Flag'))",
								"type": "Expression"
							},
							"activities": [
								{
									"name": "Lookup1",
									"type": "Lookup",
									"dependsOn": [],
									"policy": {
										"timeout": "0.12:00:00",
										"retry": 0,
										"retryIntervalInSeconds": 30,
										"secureOutput": false,
										"secureInput": false
									},
									"userProperties": [],
									"typeProperties": {
										"source": {
											"type": "AzureSqlSource",
											"sqlReaderQuery": {
												"value": "SELECT Status FROM fileStatus;",
												"type": "Expression"
											},
											"queryTimeout": "02:00:00",
											"partitionOption": "None"
										},
										"dataset": {
											"referenceName": "AzureSqlTable1",
											"type": "DatasetReference",
											"parameters": {}
										}
									}
								},
								{
									"name": "If Condition1",
									"type": "IfCondition",
									"dependsOn": [
										{
											"activity": "Lookup1",
											"dependencyConditions": [
												"Succeeded"
											]
										}
									],
									"userProperties": [],
									"typeProperties": {
										"expression": {
											"value": "@equals(activity('Lookup1').output.firstRow.status,'Y')",
											"type": "Expression"
										},
										"ifTrueActivities": [
											{
												"name": "Set variable1",
												"type": "SetVariable",
												"dependsOn": [],
												"policy": {
													"secureOutput": false,
													"secureInput": false
												},
												"userProperties": [],
												"typeProperties": {
													"variableName": "Flag",
													"value": {
														"value": "True",
														"type": "Expression"
													}
												}
											}
										]
									}
								}
							],
							"timeout": "0.12:00:00"
						}
					},
					{
						"name": "Copy data1",
						"type": "Copy",
						"state": "Inactive",
						"onInactiveMarkAs": "Succeeded",
						"dependsOn": [
							{
								"activity": "Until1",
								"dependencyConditions": [
									"Succeeded"
								]
							}
						],
						"policy": {
							"timeout": "0.12:00:00",
							"retry": 0,
							"retryIntervalInSeconds": 30,
							"secureOutput": false,
							"secureInput": false
						},
						"userProperties": [],
						"typeProperties": {
							"enableStaging": false
						}
					}
				],
				"policy": {
					"elapsedTimeMetric": {}
				},
				"variables": {
					"Flag": {
						"type": "String",
						"defaultValue": "False"
					}
				},
				"annotations": [],
				"lastPublishTime": "2025-12-28T13:26:09Z"
			},
			"dependsOn": []
		},
		{
			"name": "[concat(parameters('factoryName'), '/API_Ingestion')]",
			"type": "Microsoft.DataFactory/factories/pipelines",
			"apiVersion": "2018-06-01",
			"properties": {
				"activities": [
					{
						"name": "Copy API data",
						"type": "Copy",
						"dependsOn": [
							{
								"activity": "WebAPI Call",
								"dependencyConditions": [
									"Succeeded"
								]
							}
						],
						"policy": {
							"timeout": "0.12:00:00",
							"retry": 2,
							"retryIntervalInSeconds": 30,
							"secureOutput": false,
							"secureInput": false
						},
						"userProperties": [],
						"typeProperties": {
							"source": {
								"type": "DelimitedTextSource",
								"storeSettings": {
									"type": "HttpReadSettings",
									"requestMethod": "GET"
								},
								"formatSettings": {
									"type": "DelimitedTextReadSettings"
								}
							},
							"sink": {
								"type": "JsonSink",
								"storeSettings": {
									"type": "AzureBlobFSWriteSettings"
								},
								"formatSettings": {
									"type": "JsonWriteSettings"
								}
							},
							"enableStaging": false,
							"translator": {
								"type": "TabularTranslator",
								"mappings": [
									{
										"source": {
											"name": "airline_id",
											"type": "String"
										},
										"sink": {
											"path": "$['airline_id']"
										}
									},
									{
										"source": {
											"name": "airline_name",
											"type": "String"
										},
										"sink": {
											"path": "$['airline_name']"
										}
									},
									{
										"source": {
											"name": "country",
											"type": "String"
										},
										"sink": {
											"path": "$['country']"
										}
									}
								]
							}
						},
						"inputs": [
							{
								"referenceName": "ds_GITAPI_csv",
								"type": "DatasetReference",
								"parameters": {}
							}
						],
						"outputs": [
							{
								"referenceName": "ds_sink_json",
								"type": "DatasetReference",
								"parameters": {}
							}
						]
					},
					{
						"name": "WebAPI Call",
						"type": "WebActivity",
						"dependsOn": [],
						"policy": {
							"timeout": "0.12:00:00",
							"retry": 0,
							"retryIntervalInSeconds": 30,
							"secureOutput": false,
							"secureInput": false
						},
						"userProperties": [],
						"typeProperties": {
							"method": "GET",
							"headers": {},
							"url": {
								"value": "https://raw.githubusercontent.com/anshlambagit/AnshLambaYoutube/refs/heads/main/ADF_Project/DimAirline.csv",
								"type": "Expression"
							}
						}
					}
				],
				"policy": {
					"elapsedTimeMetric": {}
				},
				"annotations": [],
				"lastPublishTime": "2025-12-26T07:40:03Z"
			},
			"dependsOn": []
		},
		{
			"name": "[concat(parameters('factoryName'), '/Date Filename')]",
			"type": "Microsoft.DataFactory/factories/pipelines",
			"apiVersion": "2018-06-01",
			"properties": {
				"activities": [
					{
						"name": "Get Metadata1",
						"type": "GetMetadata",
						"dependsOn": [],
						"policy": {
							"timeout": "0.12:00:00",
							"retry": 0,
							"retryIntervalInSeconds": 30,
							"secureOutput": false,
							"secureInput": false
						},
						"userProperties": [],
						"typeProperties": {
							"dataset": {
								"referenceName": "ds_folder",
								"type": "DatasetReference",
								"parameters": {}
							},
							"fieldList": [
								"childItems"
							],
							"storeSettings": {
								"type": "AzureBlobFSReadSettings",
								"recursive": true,
								"enablePartitionDiscovery": false
							},
							"formatSettings": {
								"type": "DelimitedTextReadSettings"
							}
						}
					},
					{
						"name": "Filter1",
						"type": "Filter",
						"dependsOn": [
							{
								"activity": "Get Metadata1",
								"dependencyConditions": [
									"Succeeded"
								]
							}
						],
						"userProperties": [],
						"typeProperties": {
							"items": {
								"value": "@activity('Get Metadata1').output.childItems",
								"type": "Expression"
							},
							"condition": {
								"value": "@contains(item().name,'.json')",
								"type": "Expression"
							}
						}
					},
					{
						"name": "ForEach1",
						"type": "ForEach",
						"dependsOn": [
							{
								"activity": "Filter1",
								"dependencyConditions": [
									"Succeeded"
								]
							}
						],
						"userProperties": [],
						"typeProperties": {
							"items": {
								"value": "@activity('Filter1').output.Value",
								"type": "Expression"
							},
							"activities": [
								{
									"name": "Copy data1",
									"type": "Copy",
									"dependsOn": [],
									"policy": {
										"timeout": "0.12:00:00",
										"retry": 0,
										"retryIntervalInSeconds": 30,
										"secureOutput": false,
										"secureInput": false
									},
									"userProperties": [],
									"typeProperties": {
										"source": {
											"type": "JsonSource",
											"storeSettings": {
												"type": "AzureBlobFSReadSettings",
												"recursive": true,
												"enablePartitionDiscovery": false
											},
											"formatSettings": {
												"type": "JsonReadSettings"
											}
										},
										"sink": {
											"type": "JsonSink",
											"storeSettings": {
												"type": "AzureBlobFSWriteSettings"
											},
											"formatSettings": {
												"type": "JsonWriteSettings"
											}
										},
										"enableStaging": false
									},
									"inputs": [
										{
											"referenceName": "Json1",
											"type": "DatasetReference",
											"parameters": {
												"p_fileformat": {
													"value": "@item().name",
													"type": "Expression"
												}
											}
										}
									],
									"outputs": [
										{
											"referenceName": "Json2",
											"type": "DatasetReference",
											"parameters": {
												"Filename": {
													"value": "@item().name",
													"type": "Expression"
												}
											}
										}
									]
								}
							]
						}
					}
				],
				"policy": {
					"elapsedTimeMetric": {}
				},
				"annotations": [],
				"lastPublishTime": "2025-12-26T14:29:15Z"
			},
			"dependsOn": []
		},
		{
			"name": "[concat(parameters('factoryName'), '/FileInsideFolder')]",
			"type": "Microsoft.DataFactory/factories/pipelines",
			"apiVersion": "2018-06-01",
			"properties": {
				"activities": [
					{
						"name": "Get Metadata1",
						"type": "GetMetadata",
						"dependsOn": [],
						"policy": {
							"timeout": "0.12:00:00",
							"retry": 0,
							"retryIntervalInSeconds": 30,
							"secureOutput": false,
							"secureInput": false
						},
						"userProperties": [],
						"typeProperties": {
							"dataset": {
								"referenceName": "ds_folderinside",
								"type": "DatasetReference",
								"parameters": {}
							},
							"fieldList": [
								"childItems"
							],
							"storeSettings": {
								"type": "AzureBlobFSReadSettings",
								"recursive": true,
								"enablePartitionDiscovery": false
							},
							"formatSettings": {
								"type": "DelimitedTextReadSettings"
							}
						}
					},
					{
						"name": "TOchecksubfolder",
						"type": "ForEach",
						"dependsOn": [
							{
								"activity": "Get Metadata1",
								"dependencyConditions": [
									"Succeeded"
								]
							}
						],
						"userProperties": [],
						"typeProperties": {
							"items": {
								"value": "@activity('Get Metadata1').output.childItems",
								"type": "Expression"
							},
							"activities": [
								{
									"name": "InsideFolder",
									"type": "GetMetadata",
									"dependsOn": [],
									"policy": {
										"timeout": "0.12:00:00",
										"retry": 0,
										"retryIntervalInSeconds": 30,
										"secureOutput": false,
										"secureInput": false
									},
									"userProperties": [],
									"typeProperties": {
										"dataset": {
											"referenceName": "DelimitedText1",
											"type": "DatasetReference",
											"parameters": {
												"p_foldername": {
													"value": "@item().name",
													"type": "Expression"
												}
											}
										},
										"fieldList": [
											"childItems"
										],
										"storeSettings": {
											"type": "AzureBlobFSReadSettings",
											"recursive": true,
											"enablePartitionDiscovery": false
										},
										"formatSettings": {
											"type": "DelimitedTextReadSettings"
										}
									}
								},
								{
									"name": "Countnumber",
									"type": "Filter",
									"dependsOn": [
										{
											"activity": "InsideFolder",
											"dependencyConditions": [
												"Succeeded"
											]
										}
									],
									"userProperties": [],
									"typeProperties": {
										"items": {
											"value": "@activity('InsideFolder').output.childItems",
											"type": "Expression"
										},
										"condition": {
											"value": "@not(empty(item().name))",
											"type": "Expression"
										}
									}
								},
								{
									"name": "Write Number",
									"type": "Lookup",
									"dependsOn": [
										{
											"activity": "Countnumber",
											"dependencyConditions": [
												"Succeeded"
											]
										}
									],
									"policy": {
										"timeout": "0.12:00:00",
										"retry": 0,
										"retryIntervalInSeconds": 30,
										"secureOutput": false,
										"secureInput": false
									},
									"userProperties": [],
									"typeProperties": {
										"source": {
											"type": "AzureSqlSource",
											"sqlReaderQuery": {
												"value": "INSERT INTO dbo.countoffiles SELECT '@{item().name}', '@{int(activity('Countnumber').output.ItemsCount)}';\nSELECT 1 as output",
												"type": "Expression"
											},
											"queryTimeout": "02:00:00",
											"partitionOption": "None"
										},
										"dataset": {
											"referenceName": "AzureSqlTable1",
											"type": "DatasetReference",
											"parameters": {}
										}
									}
								}
							]
						}
					}
				],
				"policy": {
					"elapsedTimeMetric": {}
				},
				"annotations": [],
				"lastPublishTime": "2025-12-27T10:53:45Z"
			},
			"dependsOn": []
		},
		{
			"name": "[concat(parameters('factoryName'), '/Gold Layer')]",
			"type": "Microsoft.DataFactory/factories/pipelines",
			"apiVersion": "2018-06-01",
			"properties": {
				"activities": [
					{
						"name": "GoldDataFlow",
						"type": "ExecuteDataFlow",
						"dependsOn": [],
						"policy": {
							"timeout": "0.12:00:00",
							"retry": 0,
							"retryIntervalInSeconds": 30,
							"secureOutput": false,
							"secureInput": false
						},
						"userProperties": [],
						"typeProperties": {
							"dataflow": {
								"referenceName": "Data Serving",
								"type": "DataFlowReference",
								"parameters": {},
								"datasetParameters": {
									"DimAirline": {},
									"DimFlights": {},
									"FactBookings": {},
									"AirlineSinkGold": {},
									"FlightSinkGold": {}
								}
							},
							"staging": {},
							"compute": {
								"coreCount": 8,
								"computeType": "General"
							},
							"traceLevel": "None",
							"cacheSinks": {
								"firstRowOnly": true
							}
						}
					}
				],
				"policy": {
					"elapsedTimeMetric": {}
				},
				"annotations": [],
				"lastPublishTime": "2025-12-25T11:21:23Z"
			},
			"dependsOn": [
				"[concat(variables('factoryId'), '/dataflows/Data Serving')]"
			]
		},
		{
			"name": "[concat(parameters('factoryName'), '/Incremental')]",
			"type": "Microsoft.DataFactory/factories/pipelines",
			"apiVersion": "2018-06-01",
			"properties": {
				"activities": [
					{
						"name": "Copy data1",
						"type": "Copy",
						"dependsOn": [],
						"policy": {
							"timeout": "0.12:00:00",
							"retry": 0,
							"retryIntervalInSeconds": 30,
							"secureOutput": false,
							"secureInput": false
						},
						"userProperties": [],
						"typeProperties": {
							"source": {
								"type": "DelimitedTextSource",
								"storeSettings": {
									"type": "AzureBlobFSReadSettings",
									"recursive": true,
									"modifiedDatetimeStart": "2026-01-08T12:29:00Z",
									"modifiedDatetimeEnd": "2026-01-08T12:51:00Z",
									"wildcardFileName": "*.csv",
									"enablePartitionDiscovery": false
								},
								"formatSettings": {
									"type": "DelimitedTextReadSettings"
								}
							},
							"sink": {
								"type": "DelimitedTextSink",
								"storeSettings": {
									"type": "AzureBlobFSWriteSettings"
								},
								"formatSettings": {
									"type": "DelimitedTextWriteSettings",
									"quoteAllText": true,
									"fileExtension": ".txt"
								}
							},
							"enableStaging": false,
							"translator": {
								"type": "TabularTranslator",
								"typeConversion": true,
								"typeConversionSettings": {
									"allowDataTruncation": true,
									"treatBooleanAsNumber": false
								}
							}
						},
						"inputs": [
							{
								"referenceName": "ds_raw_gold_param",
								"type": "DatasetReference",
								"parameters": {
									"p_container": "source",
									"p_folder": "raw_gold_data"
								}
							}
						],
						"outputs": [
							{
								"referenceName": "ds_raw_gold_param",
								"type": "DatasetReference",
								"parameters": {
									"p_container": "sink",
									"p_folder": "raw_gold_data"
								}
							}
						]
					}
				],
				"policy": {
					"elapsedTimeMetric": {}
				},
				"annotations": [],
				"lastPublishTime": "2026-01-08T07:26:06Z"
			},
			"dependsOn": []
		},
		{
			"name": "[concat(parameters('factoryName'), '/SQL to Azure')]",
			"type": "Microsoft.DataFactory/factories/pipelines",
			"apiVersion": "2018-06-01",
			"properties": {
				"activities": [
					{
						"name": "Copy SQL Data",
						"type": "Copy",
						"dependsOn": [
							{
								"activity": "Last Load",
								"dependencyConditions": [
									"Succeeded"
								]
							},
							{
								"activity": "Latest Load",
								"dependencyConditions": [
									"Succeeded"
								]
							}
						],
						"policy": {
							"timeout": "0.12:00:00",
							"retry": 0,
							"retryIntervalInSeconds": 30,
							"secureOutput": false,
							"secureInput": false
						},
						"userProperties": [],
						"typeProperties": {
							"source": {
								"type": "AzureSqlSource",
								"sqlReaderQuery": {
									"value": "SELECT * FROM dbo.FactBookings\nWHERE booking_date > '@{activity('Last Load').output.firstRow.lastload}'\nAND booking_date <= '@{activity('Latest Load').output.firstRow.latestload}'",
									"type": "Expression"
								},
								"queryTimeout": "02:00:00",
								"partitionOption": "None"
							},
							"sink": {
								"type": "ParquetSink",
								"storeSettings": {
									"type": "AzureBlobFSWriteSettings"
								},
								"formatSettings": {
									"type": "ParquetWriteSettings"
								}
							},
							"enableStaging": false,
							"enableSkipIncompatibleRow": false,
							"translator": {
								"type": "TabularTranslator",
								"typeConversion": true,
								"typeConversionSettings": {
									"allowDataTruncation": true,
									"treatBooleanAsNumber": false
								}
							}
						},
						"inputs": [
							{
								"referenceName": "ds_sqlsource",
								"type": "DatasetReference",
								"parameters": {}
							}
						],
						"outputs": [
							{
								"referenceName": "ds_datalakeparq",
								"type": "DatasetReference",
								"parameters": {}
							}
						]
					},
					{
						"name": "Last Load",
						"type": "Lookup",
						"dependsOn": [],
						"policy": {
							"timeout": "0.12:00:00",
							"retry": 0,
							"retryIntervalInSeconds": 30,
							"secureOutput": false,
							"secureInput": false
						},
						"userProperties": [],
						"typeProperties": {
							"source": {
								"type": "JsonSource",
								"storeSettings": {
									"type": "AzureBlobFSReadSettings",
									"recursive": true,
									"enablePartitionDiscovery": false
								},
								"formatSettings": {
									"type": "JsonReadSettings"
								}
							},
							"dataset": {
								"referenceName": "ds_lookuplst",
								"type": "DatasetReference",
								"parameters": {}
							}
						}
					},
					{
						"name": "Latest Load",
						"type": "Lookup",
						"dependsOn": [],
						"policy": {
							"timeout": "0.12:00:00",
							"retry": 0,
							"retryIntervalInSeconds": 30,
							"secureOutput": false,
							"secureInput": false
						},
						"userProperties": [],
						"typeProperties": {
							"source": {
								"type": "AzureSqlSource",
								"sqlReaderQuery": {
									"value": "SELECT max(booking_date) as latestload\nFROM dbo.FactBookings;",
									"type": "Expression"
								},
								"queryTimeout": "02:00:00",
								"partitionOption": "None"
							},
							"dataset": {
								"referenceName": "ds_sqlsource",
								"type": "DatasetReference",
								"parameters": {}
							}
						}
					},
					{
						"name": "WaterMark",
						"type": "Copy",
						"dependsOn": [
							{
								"activity": "Copy SQL Data",
								"dependencyConditions": [
									"Succeeded"
								]
							}
						],
						"policy": {
							"timeout": "0.12:00:00",
							"retry": 0,
							"retryIntervalInSeconds": 30,
							"secureOutput": false,
							"secureInput": false
						},
						"userProperties": [],
						"typeProperties": {
							"source": {
								"type": "JsonSource",
								"additionalColumns": [
									{
										"name": "lastload",
										"value": {
											"value": "@activity('Latest Load').output.firstRow.latestload",
											"type": "Expression"
										}
									}
								],
								"storeSettings": {
									"type": "AzureBlobFSReadSettings",
									"recursive": true,
									"enablePartitionDiscovery": false
								},
								"formatSettings": {
									"type": "JsonReadSettings"
								}
							},
							"sink": {
								"type": "JsonSink",
								"storeSettings": {
									"type": "AzureBlobFSWriteSettings"
								},
								"formatSettings": {
									"type": "JsonWriteSettings"
								}
							},
							"enableStaging": false
						},
						"inputs": [
							{
								"referenceName": "ds_emptyjson",
								"type": "DatasetReference",
								"parameters": {}
							}
						],
						"outputs": [
							{
								"referenceName": "ds_lookuplst",
								"type": "DatasetReference",
								"parameters": {}
							}
						]
					}
				],
				"policy": {
					"elapsedTimeMetric": {}
				},
				"variables": {
					"v_now": {
						"type": "String"
					}
				},
				"annotations": [],
				"lastPublishTime": "2025-12-26T07:02:17Z"
			},
			"dependsOn": [
				"[concat(variables('factoryId'), '/datasets/ds_sqlsource')]"
			]
		},
		{
			"name": "[concat(parameters('factoryName'), '/bulk Azure SQL')]",
			"type": "Microsoft.DataFactory/factories/pipelines",
			"apiVersion": "2018-06-01",
			"properties": {
				"activities": [
					{
						"name": "Get List of Tables",
						"type": "Lookup",
						"dependsOn": [],
						"policy": {
							"timeout": "0.12:00:00",
							"retry": 0,
							"retryIntervalInSeconds": 30,
							"secureOutput": false,
							"secureInput": false
						},
						"userProperties": [],
						"typeProperties": {
							"source": {
								"type": "AzureSqlSource",
								"sqlReaderQuery": {
									"value": "SELECT TABLE_SCHEMA, TABLE_NAME FROM information_schema.TABLES\nWHERE TABLE_SCHEMA = 'dbo';",
									"type": "Expression"
								},
								"queryTimeout": "02:00:00",
								"partitionOption": "None"
							},
							"dataset": {
								"referenceName": "AzureSqlTable1",
								"type": "DatasetReference",
								"parameters": {}
							},
							"firstRowOnly": false
						}
					},
					{
						"name": "ForEach1",
						"type": "ForEach",
						"dependsOn": [
							{
								"activity": "Get List of Tables",
								"dependencyConditions": [
									"Succeeded"
								]
							}
						],
						"userProperties": [],
						"typeProperties": {
							"items": {
								"value": "@activity('Get List of Tables').output.value",
								"type": "Expression"
							},
							"isSequential": true,
							"activities": [
								{
									"name": "Copy data1",
									"type": "Copy",
									"dependsOn": [],
									"policy": {
										"timeout": "0.12:00:00",
										"retry": 0,
										"retryIntervalInSeconds": 30,
										"secureOutput": false,
										"secureInput": false
									},
									"userProperties": [],
									"typeProperties": {
										"source": {
											"type": "AzureSqlSource",
											"queryTimeout": "02:00:00",
											"partitionOption": "None"
										},
										"sink": {
											"type": "DelimitedTextSink",
											"storeSettings": {
												"type": "AzureBlobFSWriteSettings"
											},
											"formatSettings": {
												"type": "DelimitedTextWriteSettings",
												"quoteAllText": true,
												"fileExtension": ".txt"
											}
										},
										"enableStaging": false,
										"translator": {
											"type": "TabularTranslator",
											"typeConversion": true,
											"typeConversionSettings": {
												"allowDataTruncation": true,
												"treatBooleanAsNumber": false
											}
										}
									},
									"inputs": [
										{
											"referenceName": "Azuresqldynamic",
											"type": "DatasetReference",
											"parameters": {
												"p_schema": {
													"value": "@item().TABLE_SCHEMA",
													"type": "Expression"
												},
												"p_table": {
													"value": "@item().TABLE_NAME",
													"type": "Expression"
												}
											}
										}
									],
									"outputs": [
										{
											"referenceName": "ds_bulkcopy",
											"type": "DatasetReference",
											"parameters": {
												"p_table": {
													"value": "@concat(item().TABLE_SCHEMA,'_',item().TABLE_NAME,'.csv')",
													"type": "Expression"
												}
											}
										}
									]
								}
							]
						}
					}
				],
				"policy": {
					"elapsedTimeMetric": {}
				},
				"annotations": [],
				"lastPublishTime": "2026-01-08T09:56:09Z"
			},
			"dependsOn": []
		},
		{
			"name": "[concat(parameters('factoryName'), '/ds_onpremfile')]",
			"type": "Microsoft.DataFactory/factories/datasets",
			"apiVersion": "2018-06-01",
			"properties": {
				"linkedServiceName": {
					"referenceName": "ls_onprem_file",
					"type": "LinkedServiceReference"
				},
				"parameters": {
					"p_filename": {
						"type": "string"
					}
				},
				"annotations": [],
				"type": "DelimitedText",
				"typeProperties": {
					"location": {
						"type": "FileServerLocation",
						"fileName": {
							"value": "@dataset().p_filename",
							"type": "Expression"
						}
					},
					"columnDelimiter": ",",
					"escapeChar": "\\",
					"firstRowAsHeader": true,
					"quoteChar": "\""
				},
				"schema": []
			},
			"dependsOn": [
				"[concat(variables('factoryId'), '/linkedServices/ls_onprem_file')]"
			]
		},
		{
			"name": "[concat(parameters('factoryName'), '/Data Transformation Silver')]",
			"type": "Microsoft.DataFactory/factories/dataflows",
			"apiVersion": "2018-06-01",
			"properties": {
				"type": "MappingDataFlow",
				"typeProperties": {
					"sources": [
						{
							"dataset": {
								"referenceName": "ds_silversrc_airline",
								"type": "DatasetReference"
							},
							"name": "DimAirline"
						},
						{
							"dataset": {
								"referenceName": "ds_silversrc_flight",
								"type": "DatasetReference"
							},
							"name": "DimFlights"
						},
						{
							"dataset": {
								"referenceName": "ds_silversrc_passe",
								"type": "DatasetReference"
							},
							"name": "DimPassenger"
						},
						{
							"dataset": {
								"referenceName": "ds_silversrc_Fact",
								"type": "DatasetReference"
							},
							"name": "FactBookings"
						},
						{
							"dataset": {
								"referenceName": "ds_silversrc_git",
								"type": "DatasetReference"
							},
							"name": "GITAPI"
						}
					],
					"sinks": [
						{
							"linkedService": {
								"referenceName": "ls_datalake",
								"type": "LinkedServiceReference"
							},
							"name": "Airlinesink"
						},
						{
							"linkedService": {
								"referenceName": "ls_datalake",
								"type": "LinkedServiceReference"
							},
							"name": "sink1"
						},
						{
							"linkedService": {
								"referenceName": "ls_datalake",
								"type": "LinkedServiceReference"
							},
							"name": "sink2"
						},
						{
							"linkedService": {
								"referenceName": "ls_datalake",
								"type": "LinkedServiceReference"
							},
							"name": "sink3"
						},
						{
							"linkedService": {
								"referenceName": "ls_datalake",
								"type": "LinkedServiceReference"
							},
							"name": "sink4"
						}
					],
					"transformations": [
						{
							"name": "derivedColumn1"
						},
						{
							"name": "selectcolstimestamp"
						},
						{
							"name": "genderflag"
						},
						{
							"name": "ReplaceMale"
						},
						{
							"name": "ReplaceFemale"
						},
						{
							"name": "agegreater25"
						},
						{
							"name": "Replacespacewithunderscore"
						},
						{
							"name": "castCost"
						},
						{
							"name": "capsAirportName"
						},
						{
							"name": "UpsertDatalake"
						},
						{
							"name": "UpsertPassenger"
						},
						{
							"name": "upsertfact"
						},
						{
							"name": "upsertapi"
						},
						{
							"name": "UpsertFlight"
						}
					],
					"scriptLines": [
						"source(output(",
						"          airline_id as short,",
						"          airline_name as string,",
						"          country as string",
						"     ),",
						"     allowSchemaDrift: true,",
						"     validateSchema: false,",
						"     ignoreNoFilesFound: false) ~> DimAirline",
						"source(output(",
						"          flight_id as short,",
						"          flight_number as string,",
						"          departure_time as string,",
						"          arrival_time as string",
						"     ),",
						"     allowSchemaDrift: true,",
						"     validateSchema: false,",
						"     ignoreNoFilesFound: false) ~> DimFlights",
						"source(output(",
						"          passenger_id as short,",
						"          full_name as string,",
						"          gender as string,",
						"          age as short,",
						"          country as string",
						"     ),",
						"     allowSchemaDrift: true,",
						"     validateSchema: false,",
						"     ignoreNoFilesFound: false) ~> DimPassenger",
						"source(output(",
						"          booking_id as integer,",
						"          passenger_id as integer,",
						"          flight_id as integer,",
						"          airline_id as integer,",
						"          origin_airport_id as integer,",
						"          destination_airport_id as integer,",
						"          booking_date as date,",
						"          ticket_cost as decimal(10,2),",
						"          flight_duration_mins as integer,",
						"          checkin_status as string",
						"     ),",
						"     allowSchemaDrift: true,",
						"     validateSchema: false,",
						"     ignoreNoFilesFound: false,",
						"     format: 'parquet') ~> FactBookings",
						"source(output(",
						"          airline_id as short,",
						"          airline_name as string,",
						"          country as string",
						"     ),",
						"     allowSchemaDrift: true,",
						"     validateSchema: false,",
						"     ignoreNoFilesFound: false,",
						"     documentForm: 'documentPerLine') ~> GITAPI",
						"DimAirline derive(country = upper(country)) ~> derivedColumn1",
						"DimFlights select(mapColumn(",
						"          flight_id,",
						"          flight_number,",
						"          departure_timestamp = departure_time,",
						"          arrival_timestamp = arrival_time",
						"     ),",
						"     skipDuplicateMapInputs: true,",
						"     skipDuplicateMapOutputs: true) ~> selectcolstimestamp",
						"DimPassenger select(mapColumn(",
						"          passenger_id,",
						"          full_name,",
						"          gender_flag = gender,",
						"          age,",
						"          country",
						"     ),",
						"     skipDuplicateMapInputs: true,",
						"     skipDuplicateMapOutputs: true) ~> genderflag",
						"genderflag derive(gender_flag = regexReplace(gender_flag, \"M\", \"Male\")) ~> ReplaceMale",
						"ReplaceMale derive(gender_flag = regexReplace(gender_flag, \"F\", \"Female\")) ~> ReplaceFemale",
						"ReplaceFemale filter(age > 25 && country != \"Mexico\") ~> agegreater25",
						"agegreater25 derive(full_name = regexReplace(full_name, \" \", \"_\")) ~> Replacespacewithunderscore",
						"FactBookings cast(output(",
						"          ticket_cost as integer '000'",
						"     ),",
						"     errors: true) ~> castCost",
						"GITAPI derive(airline_name = upper(airline_name)) ~> capsAirportName",
						"derivedColumn1 alterRow(upsertIf(1==1)) ~> UpsertDatalake",
						"Replacespacewithunderscore alterRow(upsertIf(1==1)) ~> UpsertPassenger",
						"castCost alterRow(upsertIf(1==1)) ~> upsertfact",
						"capsAirportName alterRow(upsertIf(1==1)) ~> upsertapi",
						"selectcolstimestamp alterRow(upsertIf(1==1)) ~> UpsertFlight",
						"UpsertDatalake sink(allowSchemaDrift: true,",
						"     validateSchema: false,",
						"     format: 'delta',",
						"     fileSystem: 'silver',",
						"     folderPath: 'DimAirline',",
						"     mergeSchema: false,",
						"     autoCompact: false,",
						"     optimizedWrite: false,",
						"     vacuum: 0,",
						"     deletable: false,",
						"     insertable: false,",
						"     updateable: false,",
						"     upsertable: true,",
						"     keys:['airline_id'],",
						"     umask: 0022,",
						"     preCommands: [],",
						"     postCommands: [],",
						"     skipDuplicateMapInputs: true,",
						"     skipDuplicateMapOutputs: true) ~> Airlinesink",
						"UpsertFlight sink(allowSchemaDrift: true,",
						"     validateSchema: false,",
						"     format: 'delta',",
						"     fileSystem: 'silver',",
						"     folderPath: 'DimFlights',",
						"     mergeSchema: false,",
						"     autoCompact: false,",
						"     optimizedWrite: false,",
						"     vacuum: 0,",
						"     deletable: false,",
						"     insertable: false,",
						"     updateable: false,",
						"     upsertable: true,",
						"     keys:['flight_id'],",
						"     umask: 0022,",
						"     preCommands: [],",
						"     postCommands: [],",
						"     skipDuplicateMapInputs: true,",
						"     skipDuplicateMapOutputs: true) ~> sink1",
						"UpsertPassenger sink(allowSchemaDrift: true,",
						"     validateSchema: false,",
						"     format: 'delta',",
						"     fileSystem: 'silver',",
						"     folderPath: 'DimPassenger',",
						"     mergeSchema: false,",
						"     autoCompact: false,",
						"     optimizedWrite: false,",
						"     vacuum: 0,",
						"     deletable: false,",
						"     insertable: false,",
						"     updateable: false,",
						"     upsertable: true,",
						"     keys:['passenger_id'],",
						"     umask: 0022,",
						"     preCommands: [],",
						"     postCommands: [],",
						"     skipDuplicateMapInputs: true,",
						"     skipDuplicateMapOutputs: true) ~> sink2",
						"upsertfact sink(allowSchemaDrift: true,",
						"     validateSchema: false,",
						"     format: 'delta',",
						"     fileSystem: 'silver',",
						"     folderPath: 'FactBooking',",
						"     mergeSchema: false,",
						"     autoCompact: false,",
						"     optimizedWrite: false,",
						"     vacuum: 0,",
						"     deletable: false,",
						"     insertable: false,",
						"     updateable: false,",
						"     upsertable: true,",
						"     keys:['booking_id'],",
						"     umask: 0022,",
						"     preCommands: [],",
						"     postCommands: [],",
						"     skipDuplicateMapInputs: true,",
						"     skipDuplicateMapOutputs: true) ~> sink3",
						"upsertapi sink(allowSchemaDrift: true,",
						"     validateSchema: false,",
						"     format: 'delta',",
						"     fileSystem: 'silver',",
						"     folderPath: 'GITAPI',",
						"     mergeSchema: false,",
						"     autoCompact: false,",
						"     optimizedWrite: false,",
						"     vacuum: 0,",
						"     deletable: false,",
						"     insertable: false,",
						"     updateable: false,",
						"     upsertable: true,",
						"     keys:['airline_id'],",
						"     umask: 0022,",
						"     preCommands: [],",
						"     postCommands: [],",
						"     skipDuplicateMapInputs: true,",
						"     skipDuplicateMapOutputs: true) ~> sink4"
					]
				}
			},
			"dependsOn": []
		}
	]
}